flatagents/__init__.py
flatagents/actions.py
flatagents/backends.py
flatagents/baseagent.py
flatagents/distributed.py
flatagents/distributed_hooks.py
flatagents/execution.py
flatagents/flatagent.py
flatagents/flatmachine.py
flatagents/hooks.py
flatagents/locking.py
flatagents/monitoring.py
flatagents/persistence.py
flatagents/profiles.py
flatagents/run.py
flatagents/utils.py
flatagents/validation.py
flatagents/assets/README.md
flatagents/assets/__init__.py
flatagents/assets/flatagent.d.ts
flatagents/assets/flatagent.schema.json
flatagents/assets/flatagent.slim.d.ts
flatagents/assets/flatagents-runtime.d.ts
flatagents/assets/flatagents-runtime.schema.json
flatagents/assets/flatagents-runtime.slim.d.ts
flatagents/assets/flatmachine.d.ts
flatagents/assets/flatmachine.schema.json
flatagents/assets/flatmachine.slim.d.ts
flatagents/assets/profiles.d.ts
flatagents/assets/profiles.schema.json
flatagents/assets/profiles.slim.d.ts
flatagents/expressions/__init__.py
flatagents/expressions/cel.py
flatagents/expressions/simple.py
flatagents/gcp/__init__.py
flatagents/gcp/firestore.py
flatagents-0.9.0.dist-info/METADATA
flatagents-0.9.0.dist-info/WHEEL
flatagents-0.9.0.dist-info/RECORD
