Metadata-Version: 2.4
Name: flatagents
Version: 0.9.0
Summary: A lightweight framework for building LLM-powered agents and composable state machines with pluggable backends.
Project-URL: Homepage, https://github.com/memgrafter/flatagents
Project-URL: Repository, https://github.com/memgrafter/flatagents
Project-URL: Issues, https://github.com/memgrafter/flatagents/issues
Author-email: memgrafter@gmail.com
License-Expression: Apache-2.0
Keywords: agents,ai,aisuite,framework,litellm,llm
Classifier: Development Status :: 3 - Alpha
Classifier: Intended Audience :: Developers
Classifier: License :: OSI Approved :: Apache Software License
Classifier: Operating System :: OS Independent
Classifier: Programming Language :: Python :: 3
Classifier: Programming Language :: Python :: 3.10
Classifier: Programming Language :: Python :: 3.11
Classifier: Programming Language :: Python :: 3.12
Classifier: Topic :: Scientific/Engineering :: Artificial Intelligence
Requires-Python: >=3.10
Requires-Dist: aiofiles
Requires-Dist: httpx
Requires-Dist: jinja2
Requires-Dist: pyyaml
Provides-Extra: aisuite
Requires-Dist: aisuite[all]; extra == 'aisuite'
Provides-Extra: all
Requires-Dist: aisuite[all]; extra == 'all'
Requires-Dist: cel-python; extra == 'all'
Requires-Dist: jsonschema>=4.0; extra == 'all'
Requires-Dist: litellm; extra == 'all'
Requires-Dist: opentelemetry-api>=1.20.0; extra == 'all'
Requires-Dist: opentelemetry-exporter-otlp>=1.20.0; extra == 'all'
Requires-Dist: opentelemetry-sdk>=1.20.0; extra == 'all'
Provides-Extra: cel
Requires-Dist: cel-python; extra == 'cel'
Provides-Extra: gcp
Requires-Dist: aisuite[all]; extra == 'gcp'
Requires-Dist: cel-python; extra == 'gcp'
Requires-Dist: google-cloud-firestore>=2.11.0; extra == 'gcp'
Requires-Dist: jsonschema>=4.0; extra == 'gcp'
Requires-Dist: litellm; extra == 'gcp'
Requires-Dist: opentelemetry-api>=1.20.0; extra == 'gcp'
Requires-Dist: opentelemetry-exporter-otlp>=1.20.0; extra == 'gcp'
Requires-Dist: opentelemetry-sdk>=1.20.0; extra == 'gcp'
Provides-Extra: litellm
Requires-Dist: litellm; extra == 'litellm'
Provides-Extra: local
Requires-Dist: aisuite[all]; extra == 'local'
Requires-Dist: cel-python; extra == 'local'
Requires-Dist: jsonschema>=4.0; extra == 'local'
Requires-Dist: litellm; extra == 'local'
Requires-Dist: opentelemetry-api>=1.20.0; extra == 'local'
Requires-Dist: opentelemetry-exporter-otlp>=1.20.0; extra == 'local'
Requires-Dist: opentelemetry-sdk>=1.20.0; extra == 'local'
Provides-Extra: metrics
Requires-Dist: opentelemetry-api>=1.20.0; extra == 'metrics'
Requires-Dist: opentelemetry-exporter-otlp>=1.20.0; extra == 'metrics'
Requires-Dist: opentelemetry-sdk>=1.20.0; extra == 'metrics'
Provides-Extra: validation
Requires-Dist: jsonschema>=4.0; extra == 'validation'
